spacy/__init__.pxd
spacy/__init__.py
spacy/__main__.py
spacy/about.py
spacy/attrs.cp38-win_amd64.pyd
spacy/attrs.cpp
spacy/attrs.pxd
spacy/attrs.pyx
spacy/compat.py
spacy/default_config.cfg
spacy/default_config_pretraining.cfg
spacy/errors.py
spacy/git_info.py
spacy/glossary.py
spacy/kb.cp38-win_amd64.pyd
spacy/kb.cpp
spacy/kb.pxd
spacy/kb.pyx
spacy/language.py
spacy/lexeme.cp38-win_amd64.pyd
spacy/lexeme.cpp
spacy/lexeme.pxd
spacy/lexeme.pyx
spacy/lookups.py
spacy/morphology.cp38-win_amd64.pyd
spacy/morphology.cpp
spacy/morphology.pxd
spacy/morphology.pyx
spacy/parts_of_speech.cp38-win_amd64.pyd
spacy/parts_of_speech.cpp
spacy/parts_of_speech.pxd
spacy/parts_of_speech.pyx
spacy/pipe_analysis.py
spacy/schemas.py
spacy/scorer.py
spacy/strings.cp38-win_amd64.pyd
spacy/strings.cpp
spacy/strings.pxd
spacy/strings.pyx
spacy/structs.pxd
spacy/symbols.cp38-win_amd64.pyd
spacy/symbols.cpp
spacy/symbols.pxd
spacy/symbols.pyx
spacy/tokenizer.cp38-win_amd64.pyd
spacy/tokenizer.cpp
spacy/tokenizer.pxd
spacy/tokenizer.pyx
spacy/typedefs.pxd
spacy/typedefs.pyx
spacy/util.py
spacy/vectors.cp38-win_amd64.pyd
spacy/vectors.cpp
spacy/vectors.pyx
spacy/vocab.cp38-win_amd64.pyd
spacy/vocab.cpp
spacy/vocab.pxd
spacy/vocab.pyx
spacy/cli/__init__.py
spacy/cli/_util.py
spacy/cli/convert.py
spacy/cli/debug_config.py
spacy/cli/debug_data.py
spacy/cli/debug_model.py
spacy/cli/download.py
spacy/cli/evaluate.py
spacy/cli/info.py
spacy/cli/init_config.py
spacy/cli/init_pipeline.py
spacy/cli/package.py
spacy/cli/pretrain.py
spacy/cli/profile.py
spacy/cli/train.py
spacy/cli/validate.py
spacy/cli/project/__init__.py
spacy/cli/project/assets.py
spacy/cli/project/clone.py
spacy/cli/project/document.py
spacy/cli/project/dvc.py
spacy/cli/project/pull.py
spacy/cli/project/push.py
spacy/cli/project/remote_storage.py
spacy/cli/project/run.py
spacy/cli/templates/quickstart_training.jinja
spacy/cli/templates/quickstart_training_recommendations.yml
spacy/displacy/__init__.py
spacy/displacy/render.py
spacy_nightly-3.0.0a41.dist-info/LICENSE
spacy_nightly-3.0.0a41.dist-info/METADATA
spacy_nightly-3.0.0a41.dist-info/WHEEL
spacy_nightly-3.0.0a41.dist-info/entry_points.txt
spacy_nightly-3.0.0a41.dist-info/top_level.txt
spacy_nightly-3.0.0a41.dist-info/RECORD
