Metadata-Version: 2.1
Name: spacy-nightly
Version: 3.0.0a41
Summary: Industrial-strength Natural Language Processing (NLP) in Python
Home-page: https://spacy.io
Author: Explosion
Author-email: contact@explosion.ai
License: MIT
Platform: UNKNOWN
Classifier: Development Status :: 5 - Production/Stable
Classifier: Environment :: Console
Classifier: Intended Audience :: Developers
Classifier: Intended Audience :: Science/Research
Classifier: License :: OSI Approved :: MIT License
Classifier: Operating System :: POSIX :: Linux
Classifier: Operating System :: MacOS :: MacOS X
Classifier: Operating System :: Microsoft :: Windows
Classifier: Programming Language :: Cython
Classifier: Programming Language :: Python :: 3
Classifier: Programming Language :: Python :: 3.6
Classifier: Programming Language :: Python :: 3.7
Classifier: Programming Language :: Python :: 3.8
Classifier: Topic :: Scientific/Engineering
Requires-Python: >=3.6
Requires-Dist: murmurhash (<1.1.0,>=0.28.0)
Requires-Dist: cymem (<2.1.0,>=2.0.2)
Requires-Dist: preshed (<3.1.0,>=3.0.2)
Requires-Dist: thinc (<8.0.0a50,>=8.0.0a44)
Requires-Dist: blis (<0.8.0,>=0.4.0)
Requires-Dist: wasabi (<1.1.0,>=0.8.0)
Requires-Dist: srsly (<3.0.0,>=2.3.0)
Requires-Dist: catalogue (<2.1.0,>=2.0.1)
Requires-Dist: typer (<0.4.0,>=0.3.0)
Requires-Dist: pathy
Requires-Dist: tqdm (<5.0.0,>=4.38.0)
Requires-Dist: numpy (>=1.15.0)
Requires-Dist: requests (<3.0.0,>=2.13.0)
Requires-Dist: pydantic (<2.0.0,>=1.5.0)
Requires-Dist: pytokenizations
Requires-Dist: setuptools
Requires-Dist: packaging (>=20.0)
Requires-Dist: importlib-metadata (>=0.20) ; python_version < "3.8"
Requires-Dist: typing-extensions (>=3.7.4) ; python_version < "3.8"
Provides-Extra: cuda
Requires-Dist: cupy (<9.0.0,>=5.0.0b4) ; extra == 'cuda'
Provides-Extra: cuda100
Requires-Dist: cupy-cuda100 (<9.0.0,>=5.0.0b4) ; extra == 'cuda100'
Provides-Extra: cuda101
Requires-Dist: cupy-cuda101 (<9.0.0,>=5.0.0b4) ; extra == 'cuda101'
Provides-Extra: cuda102
Requires-Dist: cupy-cuda102 (<9.0.0,>=5.0.0b4) ; extra == 'cuda102'
Provides-Extra: cuda80
Requires-Dist: cupy-cuda80 (<9.0.0,>=5.0.0b4) ; extra == 'cuda80'
Provides-Extra: cuda90
Requires-Dist: cupy-cuda90 (<9.0.0,>=5.0.0b4) ; extra == 'cuda90'
Provides-Extra: cuda91
Requires-Dist: cupy-cuda91 (<9.0.0,>=5.0.0b4) ; extra == 'cuda91'
Provides-Extra: cuda92
Requires-Dist: cupy-cuda92 (<9.0.0,>=5.0.0b4) ; extra == 'cuda92'
Provides-Extra: ja
Requires-Dist: sudachipy (>=0.4.9) ; extra == 'ja'
Requires-Dist: sudachidict-core (>=20200330) ; extra == 'ja'
Provides-Extra: ko
Requires-Dist: natto-py (==0.9.0) ; extra == 'ko'
Provides-Extra: lookups
Requires-Dist: spacy-lookups-data (<1.0.0,>=1.0.0rc0) ; extra == 'lookups'
Provides-Extra: ray
Requires-Dist: spacy-ray (<1.0.0,>=0.1.0) ; extra == 'ray'
Provides-Extra: th
Requires-Dist: pythainlp (>=2.0) ; extra == 'th'
Provides-Extra: transformers
Requires-Dist: spacy-transformers (<1.0.0,>=1.0.0a22) ; extra == 'transformers'
Provides-Extra: zh
Requires-Dist: spacy-pkuseg (==0.0.26) ; extra == 'zh'
